[
    {
        "brand": "Guinness",
        "name": "Pilsner",
        "style": "Session IPA",
        "hop": "Mosaic",
        "yeast": "WLP001 - California Ale",
        "malts": "Caramel",
        "ibu": "34 IBU",
        "alcohol": "6.5%",
        "blg": "15.7\u00b0Blg",
        "user_id": "0ba4a92a-f1a0-4b7e-b7ab-0cc88491b962"
    },
    {
        "brand": "Carlsberg",
        "name": "Lager",
        "style": "Belgian Dubbel",
        "hop": "Saaz",
        "yeast": "S04 - English Ale",
        "malts": "Chocolate",
        "ibu": "59 IBU",
        "alcohol": "7.8%",
        "blg": "14.7\u00b0Blg",
        "user_id": "a36b56b7-48ae-41a6-ae14-ec7296d50f31"
    },
    {
        "brand": "Guinness",
        "name": "Pale Ale",
        "style": "Sour Ale",
        "hop": "Cascade",
        "yeast": "1388 - Belgian Strong Ale",
        "malts": "Chocolate",
        "ibu": "41 IBU",
        "alcohol": "8.3%",
        "blg": "19.2\u00b0Blg",
        "user_id": "13a31c9e-0c41-49af-ad92-60395baf8bb3"
    },
    {
        "brand": "Guinness",
        "name": "Lager",
        "style": "Belgian Dubbel",
        "hop": "Cascade",
        "yeast": "1056 - American Ale",
        "malts": "Chocolate",
        "ibu": "33 IBU",
        "alcohol": "6.4%",
        "blg": "16.0\u00b0Blg",
        "user_id": "8accbc2f-a485-4fe6-90b7-3b9907eb3fbb"
    },
    {
        "brand": "Carlsberg",
        "name": "Pilsner",
        "style": "Sour Ale",
        "hop": "Saaz",
        "yeast": "1388 - Belgian Strong Ale",
        "malts": "Caramel",
        "ibu": "53 IBU",
        "alcohol": "9.4%",
        "blg": "19.6\u00b0Blg",
        "user_id": "55f7c4ac-4553-4ac5-bb4d-1cdd52eddc94"
    },
    {
        "brand": "Guinness",
        "name": "Porter",
        "style": "Belgian Dubbel",
        "hop": "Millennium",
        "yeast": "S04 - English Ale",
        "malts": "Pilsner",
        "ibu": "35 IBU",
        "alcohol": "8.3%",
        "blg": "19.6\u00b0Blg",
        "user_id": "7412d0a9-c804-4b8d-be52-5ff6892186dc"
    },
    {
        "brand": "Guinness",
        "name": "Pale Ale",
        "style": "Session IPA",
        "hop": "Cascade",
        "yeast": "1388 - Belgian Strong Ale",
        "malts": "Pilsner",
        "ibu": "62 IBU",
        "alcohol": "5.8%",
        "blg": "15.7\u00b0Blg",
        "user_id": "610d99cb-8aff-48ac-b320-d9b95f8a910d"
    },
    {
        "brand": "Budweiser",
        "name": "Lager",
        "style": "Session IPA",
        "hop": "Saaz",
        "yeast": "1056 - American Ale",
        "malts": "Munich",
        "ibu": "30 IBU",
        "alcohol": "5.7%",
        "blg": "16.0\u00b0Blg",
        "user_id": "91846325-d3c9-4936-bf5d-c43c7c23606f"
    },
    {
        "brand": "Carlsberg",
        "name": "Pale Ale",
        "style": "Wheat Beer",
        "hop": "Cascade",
        "yeast": "WLP001 - California Ale",
        "malts": "Munich",
        "ibu": "56 IBU",
        "alcohol": "9.4%",
        "blg": "10.9\u00b0Blg",
        "user_id": "e9368666-9ea3-4122-9fd8-6412f262f87e"
    },
    {
        "brand": "Budweiser",
        "name": "Lager",
        "style": "Session IPA",
        "hop": "Millennium",
        "yeast": "S04 - English Ale",
        "malts": "Pilsner",
        "ibu": "58 IBU",
        "alcohol": "8.4%",
        "blg": "15.4\u00b0Blg",
        "user_id": "4ded2745-fff5-4962-a745-a6837f111b2d"
    },
    {
        "brand": "Guinness",
        "name": "Imperial Stout",
        "style": "Wheat Beer",
        "hop": "Cascade",
        "yeast": "1388 - Belgian Strong Ale",
        "malts": "Victory",
        "ibu": "30 IBU",
        "alcohol": "9.3%",
        "blg": "11.9\u00b0Blg",
        "user_id": "909c6730-5d1e-4206-9970-75fce0dcde47"
    },
    {
        "brand": "Guinness",
        "name": "Pale Ale",
        "style": "Strong Ale",
        "hop": "Millennium",
        "yeast": "1056 - American Ale",
        "malts": "Munich",
        "ibu": "47 IBU",
        "alcohol": "8.6%",
        "blg": "16.5\u00b0Blg",
        "user_id": "e2fe312b-1d9a-4130-ad4b-1bf3e4d6e2f3"
    },
    {
        "brand": "Budweiser",
        "name": "Lager",
        "style": "Strong Ale",
        "hop": "Cascade",
        "yeast": "1388 - Belgian Strong Ale",
        "malts": "Victory",
        "ibu": "27 IBU",
        "alcohol": "7.5%",
        "blg": "18.2\u00b0Blg",
        "user_id": "0cecee99-9a6b-433e-95ef-257449158bce"
    },
    {
        "brand": "Guinness",
        "name": "Porter",
        "style": "Session IPA",
        "hop": "Galaxy",
        "yeast": "1056 - American Ale",
        "malts": "Munich",
        "ibu": "31 IBU",
        "alcohol": "8.5%",
        "blg": "18.4\u00b0Blg",
        "user_id": "3d86bd5a-8e2e-4fac-84eb-91cf88d6b217"
    },
    {
        "brand": "Heineken",
        "name": "Lager",
        "style": "Belgian Dubbel",
        "hop": "Galaxy",
        "yeast": "1388 - Belgian Strong Ale",
        "malts": "Chocolate",
        "ibu": "68 IBU",
        "alcohol": "6.2%",
        "blg": "16.5\u00b0Blg",
        "user_id": "212178f7-8a0c-40db-8fce-d636001bd454"
    },
    {
        "brand": "Guinness",
        "name": "Imperial Stout",
        "style": "Session IPA",
        "hop": "Galaxy",
        "yeast": "W34/70 - Lager",
        "malts": "Pilsner",
        "ibu": "22 IBU",
        "alcohol": "5.2%",
        "blg": "13.0\u00b0Blg",
        "user_id": "f0657fed-5477-414b-873d-b00626588e58"
    },
    {
        "brand": "Brewdog",
        "name": "Lager",
        "style": "Wheat Beer",
        "hop": "Cascade",
        "yeast": "WLP001 - California Ale",
        "malts": "Chocolate",
        "ibu": "21 IBU",
        "alcohol": "4.0%",
        "blg": "12.2\u00b0Blg",
        "user_id": "e36c870a-4a36-450f-bf80-d96bbf609bb2"
    },
    {
        "brand": "Carlsberg",
        "name": "Pale Ale",
        "style": "Belgian Dubbel",
        "hop": "Mosaic",
        "yeast": "WLP001 - California Ale",
        "malts": "Victory",
        "ibu": "41 IBU",
        "alcohol": "4.7%",
        "blg": "11.2\u00b0Blg",
        "user_id": "38e44540-dcb8-4ca8-81dd-1b89ffb0b78f"
    },
    {
        "brand": "Budweiser",
        "name": "Lager",
        "style": "Wheat Beer",
        "hop": "Millennium",
        "yeast": "1388 - Belgian Strong Ale",
        "malts": "Victory",
        "ibu": "60 IBU",
        "alcohol": "4.5%",
        "blg": "11.0\u00b0Blg",
        "user_id": "089b7cb7-f57c-4565-9998-3943ce3d93f4"
    },
    {
        "brand": "Guinness",
        "name": "Lager",
        "style": "Session IPA",
        "hop": "Saaz",
        "yeast": "W34/70 - Lager",
        "malts": "Pilsner",
        "ibu": "54 IBU",
        "alcohol": "8.2%",
        "blg": "14.8\u00b0Blg",
        "user_id": "5d1c0ac1-9613-4618-84d7-8178142bec14"
    },
    {
        "brand": "Guinness",
        "name": "Imperial Stout",
        "style": "Sour Ale",
        "hop": "Saaz",
        "yeast": "S04 - English Ale",
        "malts": "Pilsner",
        "ibu": "60 IBU",
        "alcohol": "9.6%",
        "blg": "10.8\u00b0Blg",
        "user_id": "665a9e8f-26c1-45e7-9b09-60d35610da49"
    },
    {
        "brand": "Guinness",
        "name": "Lager",
        "style": "Belgian Dubbel",
        "hop": "Cascade",
        "yeast": "W34/70 - Lager",
        "malts": "Caramel",
        "ibu": "32 IBU",
        "alcohol": "4.8%",
        "blg": "12.6\u00b0Blg",
        "user_id": "fd086697-c3d0-42ce-a3a2-fe102b17e7a0"
    },
    {
        "brand": "Budweiser",
        "name": "Pale Ale",
        "style": "Sour Ale",
        "hop": "Galaxy",
        "yeast": "1056 - American Ale",
        "malts": "Caramel",
        "ibu": "49 IBU",
        "alcohol": "7.0%",
        "blg": "18.9\u00b0Blg",
        "user_id": "f4e5a01f-e282-4113-9185-15c5cc6dce52"
    },
    {
        "brand": "Budweiser",
        "name": "Porter",
        "style": "Sour Ale",
        "hop": "Galaxy",
        "yeast": "W34/70 - Lager",
        "malts": "Caramel",
        "ibu": "25 IBU",
        "alcohol": "6.1%",
        "blg": "17.5\u00b0Blg",
        "user_id": "da81fc3d-0475-4e8f-9523-89d0a5faa296"
    },
    {
        "brand": "Budweiser",
        "name": "Lager",
        "style": "Session IPA",
        "hop": "Cascade",
        "yeast": "1388 - Belgian Strong Ale",
        "malts": "Caramel",
        "ibu": "31 IBU",
        "alcohol": "7.3%",
        "blg": "12.6\u00b0Blg",
        "user_id": "98d2a5c8-5b92-4e81-bc16-644740f12d08"
    },
    {
        "brand": "Budweiser",
        "name": "Pilsner",
        "style": "Sour Ale",
        "hop": "Saaz",
        "yeast": "1388 - Belgian Strong Ale",
        "malts": "Chocolate",
        "ibu": "35 IBU",
        "alcohol": "5.7%",
        "blg": "12.7\u00b0Blg",
        "user_id": "c131432a-6c3d-4214-aad8-e3e949a18f10"
    },
    {
        "brand": "Heineken",
        "name": "Porter",
        "style": "Session IPA",
        "hop": "Saaz",
        "yeast": "1056 - American Ale",
        "malts": "Chocolate",
        "ibu": "67 IBU",
        "alcohol": "5.7%",
        "blg": "16.2\u00b0Blg",
        "user_id": "5b57a5d5-2b85-4f27-b9df-dcb00e87f31e"
    },
    {
        "brand": "Heineken",
        "name": "Imperial Stout",
        "style": "Belgian Dubbel",
        "hop": "Saaz",
        "yeast": "1056 - American Ale",
        "malts": "Chocolate",
        "ibu": "59 IBU",
        "alcohol": "8.2%",
        "blg": "19.1\u00b0Blg",
        "user_id": "56fb402c-7eb1-493e-8adf-ef53d8f5922c"
    },
    {
        "brand": "Brewdog",
        "name": "Pilsner",
        "style": "Session IPA",
        "hop": "Millennium",
        "yeast": "S04 - English Ale",
        "malts": "Victory",
        "ibu": "52 IBU",
        "alcohol": "6.5%",
        "blg": "18.2\u00b0Blg",
        "user_id": "44b07384-29f5-4e7e-8ccf-2f8de0fa44ec"
    },
    {
        "brand": "Heineken",
        "name": "Pilsner",
        "style": "Strong Ale",
        "hop": "Galaxy",
        "yeast": "S04 - English Ale",
        "malts": "Caramel",
        "ibu": "47 IBU",
        "alcohol": "7.8%",
        "blg": "16.9\u00b0Blg",
        "user_id": "10d191d8-4dd3-48a9-b883-dc6aa721111a"
    },
    {
        "brand": "Budweiser",
        "name": "Pale Ale",
        "style": "Belgian Dubbel",
        "hop": "Millennium",
        "yeast": "WLP001 - California Ale",
        "malts": "Pilsner",
        "ibu": "50 IBU",
        "alcohol": "4.9%",
        "blg": "11.5\u00b0Blg",
        "user_id": "8a77e04a-5377-4a47-935b-0b85daf12c67"
    },
    {
        "brand": "Guinness",
        "name": "Pilsner",
        "style": "Belgian Dubbel",
        "hop": "Saaz",
        "yeast": "1388 - Belgian Strong Ale",
        "malts": "Chocolate",
        "ibu": "65 IBU",
        "alcohol": "7.6%",
        "blg": "17.0\u00b0Blg",
        "user_id": "d70e75bb-8e31-4bc8-9dbb-25dc102fe90e"
    },
    {
        "brand": "Heineken",
        "name": "Pilsner",
        "style": "Wheat Beer",
        "hop": "Galaxy",
        "yeast": "1056 - American Ale",
        "malts": "Chocolate",
        "ibu": "33 IBU",
        "alcohol": "4.6%",
        "blg": "16.4\u00b0Blg",
        "user_id": "811ffa50-4177-401a-95e6-732d85474c40"
    },
    {
        "brand": "Brewdog",
        "name": "Lager",
        "style": "Wheat Beer",
        "hop": "Millennium",
        "yeast": "W34/70 - Lager",
        "malts": "Victory",
        "ibu": "66 IBU",
        "alcohol": "4.4%",
        "blg": "15.5\u00b0Blg",
        "user_id": "bcff5e1e-80d7-4f2e-b7cb-66472bbeff87"
    },
    {
        "brand": "Brewdog",
        "name": "Lager",
        "style": "Belgian Dubbel",
        "hop": "Cascade",
        "yeast": "1388 - Belgian Strong Ale",
        "malts": "Caramel",
        "ibu": "39 IBU",
        "alcohol": "5.7%",
        "blg": "11.5\u00b0Blg",
        "user_id": "b656ed1a-26d1-4ac4-8799-5a7cd0baf15e"
    },
    {
        "brand": "Budweiser",
        "name": "Pale Ale",
        "style": "Belgian Dubbel",
        "hop": "Saaz",
        "yeast": "WLP001 - California Ale",
        "malts": "Pilsner",
        "ibu": "60 IBU",
        "alcohol": "6.5%",
        "blg": "16.8\u00b0Blg",
        "user_id": "ff76ce34-77ec-450c-b744-54ab6186d020"
    },
    {
        "brand": "Heineken",
        "name": "Lager",
        "style": "Strong Ale",
        "hop": "Millennium",
        "yeast": "WLP001 - California Ale",
        "malts": "Chocolate",
        "ibu": "41 IBU",
        "alcohol": "5.3%",
        "blg": "12.2\u00b0Blg",
        "user_id": "f730f66e-2cc8-4d77-b923-a7734edf31e9"
    },
    {
        "brand": "Brewdog",
        "name": "Pilsner",
        "style": "Sour Ale",
        "hop": "Mosaic",
        "yeast": "W34/70 - Lager",
        "malts": "Victory",
        "ibu": "27 IBU",
        "alcohol": "6.7%",
        "blg": "14.9\u00b0Blg",
        "user_id": "5acffa55-3ff9-4acf-8cd5-980938cf16cf"
    },
    {
        "brand": "Carlsberg",
        "name": "Pilsner",
        "style": "Strong Ale",
        "hop": "Galaxy",
        "yeast": "1056 - American Ale",
        "malts": "Munich",
        "ibu": "38 IBU",
        "alcohol": "4.4%",
        "blg": "10.8\u00b0Blg",
        "user_id": "a74e9a7b-81a5-45c6-b95c-0f911c13cf29"
    },
    {
        "brand": "Brewdog",
        "name": "Porter",
        "style": "Sour Ale",
        "hop": "Mosaic",
        "yeast": "S04 - English Ale",
        "malts": "Munich",
        "ibu": "63 IBU",
        "alcohol": "9.4%",
        "blg": "10.6\u00b0Blg",
        "user_id": "4014d848-e5e2-474b-bf3d-405d98d7eb49"
    },
    {
        "brand": "Brewdog",
        "name": "Pale Ale",
        "style": "Sour Ale",
        "hop": "Galaxy",
        "yeast": "1388 - Belgian Strong Ale",
        "malts": "Chocolate",
        "ibu": "38 IBU",
        "alcohol": "5.5%",
        "blg": "15.4\u00b0Blg",
        "user_id": "3403e293-1a72-46cc-aff3-1e2db1a7daba"
    },
    {
        "brand": "Budweiser",
        "name": "Lager",
        "style": "Belgian Dubbel",
        "hop": "Cascade",
        "yeast": "WLP001 - California Ale",
        "malts": "Victory",
        "ibu": "68 IBU",
        "alcohol": "7.2%",
        "blg": "18.7\u00b0Blg",
        "user_id": "c909be81-ce4a-4001-b802-2a61960f8626"
    },
    {
        "brand": "Brewdog",
        "name": "Porter",
        "style": "Wheat Beer",
        "hop": "Saaz",
        "yeast": "W34/70 - Lager",
        "malts": "Munich",
        "ibu": "60 IBU",
        "alcohol": "8.7%",
        "blg": "15.1\u00b0Blg",
        "user_id": "35984af9-1d40-4126-8a90-e3a3e3f8e2ed"
    },
    {
        "brand": "Carlsberg",
        "name": "Pilsner",
        "style": "Session IPA",
        "hop": "Saaz",
        "yeast": "1056 - American Ale",
        "malts": "Pilsner",
        "ibu": "52 IBU",
        "alcohol": "6.3%",
        "blg": "11.6\u00b0Blg",
        "user_id": "5596f811-f47d-4133-b8e8-8ca04e55fa48"
    },
    {
        "brand": "Carlsberg",
        "name": "Lager",
        "style": "Sour Ale",
        "hop": "Mosaic",
        "yeast": "S04 - English Ale",
        "malts": "Victory",
        "ibu": "62 IBU",
        "alcohol": "9.0%",
        "blg": "12.2\u00b0Blg",
        "user_id": "8631c835-f62c-4d0b-97bd-017bd53b3a93"
    },
    {
        "brand": "Carlsberg",
        "name": "Pale Ale",
        "style": "Wheat Beer",
        "hop": "Millennium",
        "yeast": "1388 - Belgian Strong Ale",
        "malts": "Victory",
        "ibu": "39 IBU",
        "alcohol": "4.6%",
        "blg": "13.4\u00b0Blg",
        "user_id": "b205da0a-7342-4e71-afe0-f4a4987172b6"
    },
    {
        "brand": "Carlsberg",
        "name": "Pilsner",
        "style": "Strong Ale",
        "hop": "Millennium",
        "yeast": "S04 - English Ale",
        "malts": "Munich",
        "ibu": "39 IBU",
        "alcohol": "7.8%",
        "blg": "15.6\u00b0Blg",
        "user_id": "5137b65a-d810-43be-8a9f-04a6f33d4dbe"
    },
    {
        "brand": "Guinness",
        "name": "Porter",
        "style": "Sour Ale",
        "hop": "Mosaic",
        "yeast": "W34/70 - Lager",
        "malts": "Caramel",
        "ibu": "45 IBU",
        "alcohol": "4.6%",
        "blg": "13.8\u00b0Blg",
        "user_id": "784c9648-bb91-473e-8b43-ae55d6ebb37d"
    },
    {
        "brand": "Heineken",
        "name": "Porter",
        "style": "Strong Ale",
        "hop": "Cascade",
        "yeast": "W34/70 - Lager",
        "malts": "Caramel",
        "ibu": "46 IBU",
        "alcohol": "7.0%",
        "blg": "13.6\u00b0Blg",
        "user_id": "6dc91c15-d039-49dd-80d7-5ce8f6572483"
    },
    {
        "brand": "Brewdog",
        "name": "Pilsner",
        "style": "Session IPA",
        "hop": "Millennium",
        "yeast": "W34/70 - Lager",
        "malts": "Chocolate",
        "ibu": "38 IBU",
        "alcohol": "5.8%",
        "blg": "15.2\u00b0Blg",
        "user_id": "6d0d831d-ab95-4842-87f5-0a3233cf8e53"
    },
    {
        "brand": "Budweiser",
        "name": "Imperial Stout",
        "style": "Wheat Beer",
        "hop": "Mosaic",
        "yeast": "S04 - English Ale",
        "malts": "Victory",
        "ibu": "30 IBU",
        "alcohol": "8.6%",
        "blg": "15.5\u00b0Blg",
        "user_id": "29cadd39-db50-42e1-a185-6ece28aea095"
    },
    {
        "brand": "Heineken",
        "name": "Pale Ale",
        "style": "Session IPA",
        "hop": "Galaxy",
        "yeast": "1056 - American Ale",
        "malts": "Victory",
        "ibu": "58 IBU",
        "alcohol": "7.8%",
        "blg": "10.9\u00b0Blg",
        "user_id": "cc3a091d-0604-4ef7-a441-8e2395772b5e"
    },
    {
        "brand": "Carlsberg",
        "name": "Pilsner",
        "style": "Session IPA",
        "hop": "Mosaic",
        "yeast": "1388 - Belgian Strong Ale",
        "malts": "Victory",
        "ibu": "44 IBU",
        "alcohol": "8.7%",
        "blg": "11.8\u00b0Blg",
        "user_id": "a0470129-c3ec-4a65-adad-ad4bd0cfc47e"
    },
    {
        "brand": "Budweiser",
        "name": "Imperial Stout",
        "style": "Session IPA",
        "hop": "Mosaic",
        "yeast": "W34/70 - Lager",
        "malts": "Pilsner",
        "ibu": "45 IBU",
        "alcohol": "7.8%",
        "blg": "15.9\u00b0Blg",
        "user_id": "f601ea07-3dbc-4164-a0b4-2466794ca266"
    },
    {
        "brand": "Budweiser",
        "name": "Pale Ale",
        "style": "Wheat Beer",
        "hop": "Mosaic",
        "yeast": "1388 - Belgian Strong Ale",
        "malts": "Chocolate",
        "ibu": "44 IBU",
        "alcohol": "5.4%",
        "blg": "11.3\u00b0Blg",
        "user_id": "da609a3c-c2e6-452a-896b-b72a6fe8fec3"
    },
    {
        "brand": "Guinness",
        "name": "Porter",
        "style": "Session IPA",
        "hop": "Mosaic",
        "yeast": "WLP001 - California Ale",
        "malts": "Munich",
        "ibu": "50 IBU",
        "alcohol": "9.9%",
        "blg": "11.7\u00b0Blg",
        "user_id": "523b7b7f-818c-405f-87c2-08eda0044d6a"
    },
    {
        "brand": "Heineken",
        "name": "Pilsner",
        "style": "Wheat Beer",
        "hop": "Saaz",
        "yeast": "S04 - English Ale",
        "malts": "Caramel",
        "ibu": "68 IBU",
        "alcohol": "7.3%",
        "blg": "19.5\u00b0Blg",
        "user_id": "8179640a-fcba-4285-aac5-bef4f017fb74"
    },
    {
        "brand": "Heineken",
        "name": "Pilsner",
        "style": "Sour Ale",
        "hop": "Cascade",
        "yeast": "S04 - English Ale",
        "malts": "Chocolate",
        "ibu": "21 IBU",
        "alcohol": "5.4%",
        "blg": "18.9\u00b0Blg",
        "user_id": "0fb9b9ed-6e4e-4604-9dd8-cc6e91d250f3"
    },
    {
        "brand": "Guinness",
        "name": "Porter",
        "style": "Wheat Beer",
        "hop": "Galaxy",
        "yeast": "WLP001 - California Ale",
        "malts": "Munich",
        "ibu": "36 IBU",
        "alcohol": "9.2%",
        "blg": "10.1\u00b0Blg",
        "user_id": "23494915-fa8b-4a9d-8b5f-3de58868df14"
    },
    {
        "brand": "Budweiser",
        "name": "Lager",
        "style": "Session IPA",
        "hop": "Galaxy",
        "yeast": "WLP001 - California Ale",
        "malts": "Munich",
        "ibu": "52 IBU",
        "alcohol": "9.7%",
        "blg": "16.0\u00b0Blg",
        "user_id": "e8977444-230a-4cb1-9db8-1099422fd31c"
    },
    {
        "brand": "Guinness",
        "name": "Imperial Stout",
        "style": "Sour Ale",
        "hop": "Saaz",
        "yeast": "W34/70 - Lager",
        "malts": "Caramel",
        "ibu": "49 IBU",
        "alcohol": "8.8%",
        "blg": "17.7\u00b0Blg",
        "user_id": "70df799b-3059-4337-8178-79d234bd2724"
    },
    {
        "brand": "Heineken",
        "name": "Imperial Stout",
        "style": "Strong Ale",
        "hop": "Saaz",
        "yeast": "1056 - American Ale",
        "malts": "Munich",
        "ibu": "34 IBU",
        "alcohol": "4.8%",
        "blg": "16.6\u00b0Blg",
        "user_id": "4247a5c7-6464-4614-a704-b06e37a21164"
    },
    {
        "brand": "Guinness",
        "name": "Pilsner",
        "style": "Belgian Dubbel",
        "hop": "Millennium",
        "yeast": "1056 - American Ale",
        "malts": "Munich",
        "ibu": "21 IBU",
        "alcohol": "7.9%",
        "blg": "15.0\u00b0Blg",
        "user_id": "84d10104-9c76-456a-8167-5314584600c9"
    },
    {
        "brand": "Budweiser",
        "name": "Imperial Stout",
        "style": "Sour Ale",
        "hop": "Mosaic",
        "yeast": "S04 - English Ale",
        "malts": "Caramel",
        "ibu": "27 IBU",
        "alcohol": "5.1%",
        "blg": "17.3\u00b0Blg",
        "user_id": "ebbe8c59-06f8-4747-8c4c-f816f8318926"
    },
    {
        "brand": "Carlsberg",
        "name": "Lager",
        "style": "Belgian Dubbel",
        "hop": "Millennium",
        "yeast": "WLP001 - California Ale",
        "malts": "Pilsner",
        "ibu": "54 IBU",
        "alcohol": "5.0%",
        "blg": "15.1\u00b0Blg",
        "user_id": "976908d7-87ea-471d-a4c3-7789fde134c9"
    },
    {
        "brand": "Guinness",
        "name": "Imperial Stout",
        "style": "Belgian Dubbel",
        "hop": "Millennium",
        "yeast": "S04 - English Ale",
        "malts": "Caramel",
        "ibu": "49 IBU",
        "alcohol": "4.9%",
        "blg": "16.6\u00b0Blg",
        "user_id": "9bf17a8d-7c94-4c0d-aa5b-fc9b1da9ba57"
    },
    {
        "brand": "Guinness",
        "name": "Pale Ale",
        "style": "Wheat Beer",
        "hop": "Millennium",
        "yeast": "W34/70 - Lager",
        "malts": "Caramel",
        "ibu": "66 IBU",
        "alcohol": "5.7%",
        "blg": "17.6\u00b0Blg",
        "user_id": "5f7c21d8-05b8-4945-a411-4ee9c888bedd"
    },
    {
        "brand": "Budweiser",
        "name": "Porter",
        "style": "Session IPA",
        "hop": "Millennium",
        "yeast": "1056 - American Ale",
        "malts": "Chocolate",
        "ibu": "66 IBU",
        "alcohol": "8.0%",
        "blg": "19.9\u00b0Blg",
        "user_id": "ef4df3ab-db44-45c8-82eb-a8f5ab997c1c"
    },
    {
        "brand": "Heineken",
        "name": "Lager",
        "style": "Belgian Dubbel",
        "hop": "Mosaic",
        "yeast": "WLP001 - California Ale",
        "malts": "Pilsner",
        "ibu": "27 IBU",
        "alcohol": "10.0%",
        "blg": "15.7\u00b0Blg",
        "user_id": "f6e2b1ba-94e3-4892-83e3-2c0b581e6270"
    },
    {
        "brand": "Guinness",
        "name": "Imperial Stout",
        "style": "Wheat Beer",
        "hop": "Millennium",
        "yeast": "WLP001 - California Ale",
        "malts": "Munich",
        "ibu": "68 IBU",
        "alcohol": "8.1%",
        "blg": "17.3\u00b0Blg",
        "user_id": "ba7d3949-0f60-4272-bcd7-d04bcd69a9c4"
    },
    {
        "brand": "Budweiser",
        "name": "Imperial Stout",
        "style": "Wheat Beer",
        "hop": "Mosaic",
        "yeast": "WLP001 - California Ale",
        "malts": "Victory",
        "ibu": "22 IBU",
        "alcohol": "5.4%",
        "blg": "17.2\u00b0Blg",
        "user_id": "a4729d5c-f6d3-4778-9dd7-33f76c0e7352"
    },
    {
        "brand": "Heineken",
        "name": "Pilsner",
        "style": "Session IPA",
        "hop": "Cascade",
        "yeast": "W34/70 - Lager",
        "malts": "Munich",
        "ibu": "58 IBU",
        "alcohol": "5.8%",
        "blg": "13.7\u00b0Blg",
        "user_id": "a8174588-bcc6-4ac7-9cf8-d31d5a252075"
    },
    {
        "brand": "Guinness",
        "name": "Pale Ale",
        "style": "Belgian Dubbel",
        "hop": "Cascade",
        "yeast": "W34/70 - Lager",
        "malts": "Victory",
        "ibu": "32 IBU",
        "alcohol": "9.6%",
        "blg": "17.8\u00b0Blg",
        "user_id": "ac5d3b56-a0c3-4d7a-b395-e811bfd53068"
    },
    {
        "brand": "Brewdog",
        "name": "Lager",
        "style": "Session IPA",
        "hop": "Mosaic",
        "yeast": "W34/70 - Lager",
        "malts": "Pilsner",
        "ibu": "33 IBU",
        "alcohol": "6.1%",
        "blg": "19.5\u00b0Blg",
        "user_id": "04ee0254-2b11-4a41-b401-d8af29aa6c1a"
    },
    {
        "brand": "Heineken",
        "name": "Porter",
        "style": "Wheat Beer",
        "hop": "Millennium",
        "yeast": "1056 - American Ale",
        "malts": "Chocolate",
        "ibu": "66 IBU",
        "alcohol": "7.9%",
        "blg": "18.0\u00b0Blg",
        "user_id": "d874a571-57e1-4cb7-8536-d97ed23bf280"
    },
    {
        "brand": "Carlsberg",
        "name": "Pale Ale",
        "style": "Wheat Beer",
        "hop": "Cascade",
        "yeast": "W34/70 - Lager",
        "malts": "Caramel",
        "ibu": "25 IBU",
        "alcohol": "9.2%",
        "blg": "14.0\u00b0Blg",
        "user_id": "3812c8bc-f6a7-4eb5-8910-3b0ec6963fd1"
    },
    {
        "brand": "Carlsberg",
        "name": "Pilsner",
        "style": "Wheat Beer",
        "hop": "Cascade",
        "yeast": "WLP001 - California Ale",
        "malts": "Caramel",
        "ibu": "49 IBU",
        "alcohol": "5.4%",
        "blg": "12.0\u00b0Blg",
        "user_id": "d62d9c20-2e33-4b45-91c4-d00fcb830d54"
    },
    {
        "brand": "Budweiser",
        "name": "Pilsner",
        "style": "Wheat Beer",
        "hop": "Millennium",
        "yeast": "1056 - American Ale",
        "malts": "Munich",
        "ibu": "53 IBU",
        "alcohol": "4.6%",
        "blg": "11.7\u00b0Blg",
        "user_id": "f8c843fd-2a43-43cf-8899-b7e169e18e13"
    },
    {
        "brand": "Brewdog",
        "name": "Lager",
        "style": "Strong Ale",
        "hop": "Mosaic",
        "yeast": "W34/70 - Lager",
        "malts": "Victory",
        "ibu": "44 IBU",
        "alcohol": "6.1%",
        "blg": "16.5\u00b0Blg",
        "user_id": "c5c87b17-b807-4fcb-aa68-55833b89d00e"
    },
    {
        "brand": "Brewdog",
        "name": "Porter",
        "style": "Session IPA",
        "hop": "Mosaic",
        "yeast": "1388 - Belgian Strong Ale",
        "malts": "Munich",
        "ibu": "44 IBU",
        "alcohol": "4.9%",
        "blg": "10.1\u00b0Blg",
        "user_id": "705a7df9-5555-4ece-8acc-18ee39f635a0"
    },
    {
        "brand": "Carlsberg",
        "name": "Porter",
        "style": "Wheat Beer",
        "hop": "Saaz",
        "yeast": "WLP001 - California Ale",
        "malts": "Pilsner",
        "ibu": "51 IBU",
        "alcohol": "4.0%",
        "blg": "12.8\u00b0Blg",
        "user_id": "54de5282-bbca-4f74-9ff9-494d7550dfe1"
    },
    {
        "brand": "Brewdog",
        "name": "Lager",
        "style": "Strong Ale",
        "hop": "Saaz",
        "yeast": "WLP001 - California Ale",
        "malts": "Pilsner",
        "ibu": "55 IBU",
        "alcohol": "7.7%",
        "blg": "15.4\u00b0Blg",
        "user_id": "f26a97b7-5391-4969-9012-cbb06c7fba1f"
    },
    {
        "brand": "Brewdog",
        "name": "Pale Ale",
        "style": "Sour Ale",
        "hop": "Cascade",
        "yeast": "1056 - American Ale",
        "malts": "Munich",
        "ibu": "62 IBU",
        "alcohol": "5.8%",
        "blg": "15.3\u00b0Blg",
        "user_id": "04681b72-620c-4db6-97b5-b406947e25ec"
    },
    {
        "brand": "Brewdog",
        "name": "Porter",
        "style": "Session IPA",
        "hop": "Mosaic",
        "yeast": "S04 - English Ale",
        "malts": "Munich",
        "ibu": "67 IBU",
        "alcohol": "4.9%",
        "blg": "12.8\u00b0Blg",
        "user_id": "c58865c2-8315-4e6b-b07e-5d5aeaf1250a"
    },
    {
        "brand": "Heineken",
        "name": "Lager",
        "style": "Strong Ale",
        "hop": "Cascade",
        "yeast": "W34/70 - Lager",
        "malts": "Pilsner",
        "ibu": "24 IBU",
        "alcohol": "6.4%",
        "blg": "13.4\u00b0Blg",
        "user_id": "d02f7a77-bbb8-4613-ab2d-5bebb2ee9bd6"
    },
    {
        "brand": "Carlsberg",
        "name": "Porter",
        "style": "Belgian Dubbel",
        "hop": "Mosaic",
        "yeast": "1388 - Belgian Strong Ale",
        "malts": "Caramel",
        "ibu": "24 IBU",
        "alcohol": "7.6%",
        "blg": "17.6\u00b0Blg",
        "user_id": "8ccd1b0a-4dac-4100-a8cc-305839f4b61f"
    },
    {
        "brand": "Brewdog",
        "name": "Imperial Stout",
        "style": "Strong Ale",
        "hop": "Cascade",
        "yeast": "W34/70 - Lager",
        "malts": "Chocolate",
        "ibu": "65 IBU",
        "alcohol": "5.0%",
        "blg": "12.1\u00b0Blg",
        "user_id": "39bef89b-abca-474d-a4c7-85ccd7c23458"
    },
    {
        "brand": "Budweiser",
        "name": "Porter",
        "style": "Strong Ale",
        "hop": "Mosaic",
        "yeast": "1388 - Belgian Strong Ale",
        "malts": "Pilsner",
        "ibu": "65 IBU",
        "alcohol": "7.7%",
        "blg": "11.5\u00b0Blg",
        "user_id": "c9f552db-f69e-4031-8096-947824b2a455"
    },
    {
        "brand": "Heineken",
        "name": "Imperial Stout",
        "style": "Belgian Dubbel",
        "hop": "Cascade",
        "yeast": "1056 - American Ale",
        "malts": "Caramel",
        "ibu": "44 IBU",
        "alcohol": "9.3%",
        "blg": "16.5\u00b0Blg",
        "user_id": "d6b4a3b4-6e3e-41b2-95c7-c060c2feb2cc"
    },
    {
        "brand": "Budweiser",
        "name": "Pale Ale",
        "style": "Session IPA",
        "hop": "Mosaic",
        "yeast": "S04 - English Ale",
        "malts": "Caramel",
        "ibu": "41 IBU",
        "alcohol": "7.2%",
        "blg": "14.0\u00b0Blg",
        "user_id": "322a127d-0cda-46cc-9d01-520ac79d6ca1"
    },
    {
        "brand": "Carlsberg",
        "name": "Imperial Stout",
        "style": "Sour Ale",
        "hop": "Galaxy",
        "yeast": "1056 - American Ale",
        "malts": "Munich",
        "ibu": "67 IBU",
        "alcohol": "8.6%",
        "blg": "18.9\u00b0Blg",
        "user_id": "ff3b3a8d-ca4b-4c85-a19f-1a88b0d25ac7"
    },
    {
        "brand": "Heineken",
        "name": "Pale Ale",
        "style": "Wheat Beer",
        "hop": "Millennium",
        "yeast": "W34/70 - Lager",
        "malts": "Caramel",
        "ibu": "59 IBU",
        "alcohol": "5.2%",
        "blg": "11.3\u00b0Blg",
        "user_id": "58eee8b9-1cfa-45a3-ab22-674645447fed"
    },
    {
        "brand": "Budweiser",
        "name": "Imperial Stout",
        "style": "Sour Ale",
        "hop": "Galaxy",
        "yeast": "1388 - Belgian Strong Ale",
        "malts": "Chocolate",
        "ibu": "57 IBU",
        "alcohol": "8.1%",
        "blg": "14.3\u00b0Blg",
        "user_id": "9efb180b-6e82-49b7-828c-4e817c14e072"
    },
    {
        "brand": "Budweiser",
        "name": "Pilsner",
        "style": "Belgian Dubbel",
        "hop": "Saaz",
        "yeast": "1056 - American Ale",
        "malts": "Pilsner",
        "ibu": "42 IBU",
        "alcohol": "4.3%",
        "blg": "19.9\u00b0Blg",
        "user_id": "7a241665-048b-4c58-8c48-4692e007fad5"
    },
    {
        "brand": "Heineken",
        "name": "Lager",
        "style": "Session IPA",
        "hop": "Cascade",
        "yeast": "1056 - American Ale",
        "malts": "Victory",
        "ibu": "26 IBU",
        "alcohol": "8.9%",
        "blg": "14.7\u00b0Blg",
        "user_id": "dd40d76d-c0f2-4ce3-a8f8-2af812d98cc5"
    },
    {
        "brand": "Budweiser",
        "name": "Porter",
        "style": "Belgian Dubbel",
        "hop": "Cascade",
        "yeast": "1388 - Belgian Strong Ale",
        "malts": "Pilsner",
        "ibu": "34 IBU",
        "alcohol": "4.7%",
        "blg": "18.0\u00b0Blg",
        "user_id": "d89db9b4-c4cc-43b6-84e3-2fee577ba5b5"
    },
    {
        "brand": "Guinness",
        "name": "Porter",
        "style": "Session IPA",
        "hop": "Millennium",
        "yeast": "W34/70 - Lager",
        "malts": "Munich",
        "ibu": "38 IBU",
        "alcohol": "4.6%",
        "blg": "18.6\u00b0Blg",
        "user_id": "4a97eb38-5af2-4f40-b7df-63ea0b950611"
    },
    {
        "brand": "Brewdog",
        "name": "Pilsner",
        "style": "Session IPA",
        "hop": "Saaz",
        "yeast": "1388 - Belgian Strong Ale",
        "malts": "Chocolate",
        "ibu": "51 IBU",
        "alcohol": "6.6%",
        "blg": "14.7\u00b0Blg",
        "user_id": "6897f0e7-9acf-41b2-9a81-e4b4c89b427e"
    },
    {
        "brand": "Heineken",
        "name": "Pilsner",
        "style": "Belgian Dubbel",
        "hop": "Galaxy",
        "yeast": "1056 - American Ale",
        "malts": "Munich",
        "ibu": "44 IBU",
        "alcohol": "4.4%",
        "blg": "18.1\u00b0Blg",
        "user_id": "d4f42a28-0260-4714-94c9-91cd44835454"
    },
    {
        "brand": "Guinness",
        "name": "Imperial Stout",
        "style": "Sour Ale",
        "hop": "Millennium",
        "yeast": "1056 - American Ale",
        "malts": "Pilsner",
        "ibu": "23 IBU",
        "alcohol": "4.5%",
        "blg": "12.6\u00b0Blg",
        "user_id": "bece84f9-f04c-41da-b0d4-daaa1a60c109"
    }
]