[
    {
        "id": 3770,
        "uid": "93a3407d-2a36-4474-bd1a-0d2d37cb45be",
        "valid_card": "5173-7819-2454-6298",
        "token": "tok_visa",
        "invalid_card": "4000000000000044",
        "month": "01",
        "year": "2029",
        "ccv": "152",
        "ccv_amex": "7314",
        "user_id": "0ba4a92a-f1a0-4b7e-b7ab-0cc88491b962",
        "dt_current_timestamp": "2024-01-17 20:09:47"
    },
    {
        "id": 2040,
        "uid": "c3aef9a9-e333-49f6-8a20-98092704e3e7",
        "valid_card": "8731-3524-7244-5445",
        "token": "tok_discover",
        "invalid_card": "4000000000000044",
        "month": "01",
        "year": "2022",
        "ccv": "975",
        "ccv_amex": "4575",
        "user_id": "a36b56b7-48ae-41a6-ae14-ec7296d50f31",
        "dt_current_timestamp": "2024-01-17 20:09:47"
    },
    {
        "id": 2394,
        "uid": "02282df4-d704-4a54-93f3-f99bf2513d05",
        "valid_card": "7438-9048-7692-3483",
        "token": "tok_discover",
        "invalid_card": "4000000000000044",
        "month": "01",
        "year": "2030",
        "ccv": "105",
        "ccv_amex": "6425",
        "user_id": "13a31c9e-0c41-49af-ad92-60395baf8bb3",
        "dt_current_timestamp": "2024-01-17 20:09:47"
    },
    {
        "id": 4773,
        "uid": "99c2c6ae-0d47-452f-b769-82dd471a099f",
        "valid_card": "6302-6525-2720-7271",
        "token": "tok_discover",
        "invalid_card": "4000000000000101",
        "month": "07",
        "year": "2027",
        "ccv": "568",
        "ccv_amex": "2032",
        "user_id": "8accbc2f-a485-4fe6-90b7-3b9907eb3fbb",
        "dt_current_timestamp": "2024-01-17 20:09:47"
    },
    {
        "id": 8701,
        "uid": "3195f038-87d8-4ede-af1d-7003c084abc1",
        "valid_card": "2303-4181-7497-3532",
        "token": "tok_discover",
        "invalid_card": "4000000000000044",
        "month": "09",
        "year": "2030",
        "ccv": "266",
        "ccv_amex": "5726",
        "user_id": "55f7c4ac-4553-4ac5-bb4d-1cdd52eddc94",
        "dt_current_timestamp": "2024-01-17 20:09:47"
    },
    {
        "id": 1561,
        "uid": "c284e8ee-7b2a-4d31-b1fd-da623f307714",
        "valid_card": "8824-2306-7536-8254",
        "token": "tok_discover",
        "invalid_card": "4000000000000028",
        "month": "08",
        "year": "2021",
        "ccv": "444",
        "ccv_amex": "3674",
        "user_id": "7412d0a9-c804-4b8d-be52-5ff6892186dc",
        "dt_current_timestamp": "2024-01-17 20:09:47"
    },
    {
        "id": 2267,
        "uid": "c715d4b3-7a7f-4dbe-85d5-904148df37c1",
        "valid_card": "1340-6066-7887-7609",
        "token": "tok_mastercard",
        "invalid_card": "4000000000000044",
        "month": "06",
        "year": "2027",
        "ccv": "113",
        "ccv_amex": "7285",
        "user_id": "610d99cb-8aff-48ac-b320-d9b95f8a910d",
        "dt_current_timestamp": "2024-01-17 20:09:47"
    },
    {
        "id": 4220,
        "uid": "268a87fb-986f-4b4f-92f7-19b6ac662764",
        "valid_card": "3086-2345-6709-6814",
        "token": "tok_visa",
        "invalid_card": "4000000000000101",
        "month": "01",
        "year": "2025",
        "ccv": "261",
        "ccv_amex": "4765",
        "user_id": "91846325-d3c9-4936-bf5d-c43c7c23606f",
        "dt_current_timestamp": "2024-01-17 20:09:47"
    },
    {
        "id": 4810,
        "uid": "22adc7e3-0310-4bb1-aa0c-9a2d7228005a",
        "valid_card": "2776-3340-9229-2103",
        "token": "tok_visa",
        "invalid_card": "4000000000000044",
        "month": "04",
        "year": "2021",
        "ccv": "913",
        "ccv_amex": "6895",
        "user_id": "e9368666-9ea3-4122-9fd8-6412f262f87e",
        "dt_current_timestamp": "2024-01-17 20:09:47"
    },
    {
        "id": 2792,
        "uid": "f7476b58-7fa1-4838-8220-40077122aa78",
        "valid_card": "3734-7983-4814-7179",
        "token": "tok_discover",
        "invalid_card": "4000000000000044",
        "month": "07",
        "year": "2024",
        "ccv": "650",
        "ccv_amex": "6700",
        "user_id": "4ded2745-fff5-4962-a745-a6837f111b2d",
        "dt_current_timestamp": "2024-01-17 20:09:47"
    },
    {
        "id": 7813,
        "uid": "766e4c9a-9a6a-4693-9d1a-efb4ecc3ca20",
        "valid_card": "4575-6686-5950-6298",
        "token": "tok_mastercard",
        "invalid_card": "4000000000000044",
        "month": "12",
        "year": "2029",
        "ccv": "783",
        "ccv_amex": "4958",
        "user_id": "909c6730-5d1e-4206-9970-75fce0dcde47",
        "dt_current_timestamp": "2024-01-17 20:09:47"
    },
    {
        "id": 6367,
        "uid": "e9dca637-9510-4d16-bc13-6dd6284251be",
        "valid_card": "3586-7688-9375-1962",
        "token": "tok_mastercard",
        "invalid_card": "4000000000000101",
        "month": "11",
        "year": "2025",
        "ccv": "267",
        "ccv_amex": "1948",
        "user_id": "e2fe312b-1d9a-4130-ad4b-1bf3e4d6e2f3",
        "dt_current_timestamp": "2024-01-17 20:09:47"
    },
    {
        "id": 2021,
        "uid": "dc58ef29-8ac0-4172-b737-303e1aeaa82b",
        "valid_card": "8375-7268-3174-3077",
        "token": "tok_visa",
        "invalid_card": "4000000000000101",
        "month": "01",
        "year": "2022",
        "ccv": "224",
        "ccv_amex": "5228",
        "user_id": "0cecee99-9a6b-433e-95ef-257449158bce",
        "dt_current_timestamp": "2024-01-17 20:09:47"
    },
    {
        "id": 1715,
        "uid": "b02a7986-2c2d-46cd-814e-70f3b799a166",
        "valid_card": "4419-7489-5555-1649",
        "token": "tok_mastercard",
        "invalid_card": "4000000000000028",
        "month": "07",
        "year": "2023",
        "ccv": "460",
        "ccv_amex": "7911",
        "user_id": "3d86bd5a-8e2e-4fac-84eb-91cf88d6b217",
        "dt_current_timestamp": "2024-01-17 20:09:47"
    },
    {
        "id": 6857,
        "uid": "e83e5643-66bf-4b2f-949f-0a7732f692df",
        "valid_card": "3576-8322-5571-4023",
        "token": "tok_mastercard",
        "invalid_card": "4000000000000044",
        "month": "06",
        "year": "2027",
        "ccv": "219",
        "ccv_amex": "5694",
        "user_id": "212178f7-8a0c-40db-8fce-d636001bd454",
        "dt_current_timestamp": "2024-01-17 20:09:47"
    },
    {
        "id": 3769,
        "uid": "edac5d2c-8bf9-4f17-8a6d-31d12137af13",
        "valid_card": "9401-2304-2884-6516",
        "token": "tok_visa",
        "invalid_card": "4000000000000028",
        "month": "03",
        "year": "2026",
        "ccv": "409",
        "ccv_amex": "9231",
        "user_id": "f0657fed-5477-414b-873d-b00626588e58",
        "dt_current_timestamp": "2024-01-17 20:09:47"
    },
    {
        "id": 2566,
        "uid": "79372188-bfe5-45b3-be07-c78f6aedf9c6",
        "valid_card": "5475-7630-2093-4907",
        "token": "tok_visa",
        "invalid_card": "4000000000000101",
        "month": "12",
        "year": "2026",
        "ccv": "852",
        "ccv_amex": "9540",
        "user_id": "e36c870a-4a36-450f-bf80-d96bbf609bb2",
        "dt_current_timestamp": "2024-01-17 20:09:47"
    },
    {
        "id": 7158,
        "uid": "349d90f5-d65f-4465-b9d8-0f3df73e10dd",
        "valid_card": "8428-9639-5813-3750",
        "token": "tok_mastercard",
        "invalid_card": "4000000000000101",
        "month": "03",
        "year": "2023",
        "ccv": "458",
        "ccv_amex": "4465",
        "user_id": "38e44540-dcb8-4ca8-81dd-1b89ffb0b78f",
        "dt_current_timestamp": "2024-01-17 20:09:47"
    },
    {
        "id": 7112,
        "uid": "dcc64025-7232-47be-95eb-24196b379806",
        "valid_card": "7017-2707-6156-6139",
        "token": "tok_mastercard",
        "invalid_card": "4000000000000028",
        "month": "03",
        "year": "2025",
        "ccv": "852",
        "ccv_amex": "6136",
        "user_id": "089b7cb7-f57c-4565-9998-3943ce3d93f4",
        "dt_current_timestamp": "2024-01-17 20:09:47"
    },
    {
        "id": 6637,
        "uid": "2c7c4ea2-fbb6-49bd-a39f-920736eaef33",
        "valid_card": "2981-5306-9875-9436",
        "token": "tok_discover",
        "invalid_card": "4000000000000044",
        "month": "09",
        "year": "2027",
        "ccv": "587",
        "ccv_amex": "3663",
        "user_id": "5d1c0ac1-9613-4618-84d7-8178142bec14",
        "dt_current_timestamp": "2024-01-17 20:09:47"
    },
    {
        "id": 3155,
        "uid": "5553d3cf-4294-4dfb-97ac-bfac10adb06c",
        "valid_card": "3926-6634-1263-4461",
        "token": "tok_discover",
        "invalid_card": "4000000000000101",
        "month": "04",
        "year": "2026",
        "ccv": "234",
        "ccv_amex": "9383",
        "user_id": "665a9e8f-26c1-45e7-9b09-60d35610da49",
        "dt_current_timestamp": "2024-01-17 20:09:47"
    },
    {
        "id": 1548,
        "uid": "958147b9-9968-4f37-af3d-490f5daee12a",
        "valid_card": "7436-7058-8062-6206",
        "token": "tok_visa",
        "invalid_card": "4000000000000028",
        "month": "04",
        "year": "2024",
        "ccv": "922",
        "ccv_amex": "2072",
        "user_id": "fd086697-c3d0-42ce-a3a2-fe102b17e7a0",
        "dt_current_timestamp": "2024-01-17 20:09:47"
    },
    {
        "id": 6962,
        "uid": "44d2501d-7ae1-4a95-9b27-780e032ffeeb",
        "valid_card": "3373-8115-1889-3950",
        "token": "tok_visa",
        "invalid_card": "4000000000000044",
        "month": "05",
        "year": "2026",
        "ccv": "976",
        "ccv_amex": "4552",
        "user_id": "f4e5a01f-e282-4113-9185-15c5cc6dce52",
        "dt_current_timestamp": "2024-01-17 20:09:47"
    },
    {
        "id": 2024,
        "uid": "5a893954-61d1-41db-8bab-439b5bfd3402",
        "valid_card": "2439-4591-3268-8686",
        "token": "tok_discover",
        "invalid_card": "4000000000000028",
        "month": "01",
        "year": "2028",
        "ccv": "501",
        "ccv_amex": "6718",
        "user_id": "da81fc3d-0475-4e8f-9523-89d0a5faa296",
        "dt_current_timestamp": "2024-01-17 20:09:47"
    },
    {
        "id": 7652,
        "uid": "b3099b0c-65ed-4318-a3be-074aa1009df9",
        "valid_card": "1497-6925-3969-2094",
        "token": "tok_visa",
        "invalid_card": "4000000000000044",
        "month": "03",
        "year": "2029",
        "ccv": "514",
        "ccv_amex": "5130",
        "user_id": "98d2a5c8-5b92-4e81-bc16-644740f12d08",
        "dt_current_timestamp": "2024-01-17 20:09:47"
    },
    {
        "id": 8497,
        "uid": "d3390088-59c5-4c23-a20c-22b256a3ee5b",
        "valid_card": "5370-6251-2326-9883",
        "token": "tok_mastercard",
        "invalid_card": "4000000000000044",
        "month": "04",
        "year": "2021",
        "ccv": "550",
        "ccv_amex": "7967",
        "user_id": "c131432a-6c3d-4214-aad8-e3e949a18f10",
        "dt_current_timestamp": "2024-01-17 20:09:47"
    },
    {
        "id": 8004,
        "uid": "c4dcfeb8-cbfc-4f40-ac2f-611e5f4e73af",
        "valid_card": "5539-3666-4564-4248",
        "token": "tok_discover",
        "invalid_card": "4000000000000044",
        "month": "05",
        "year": "2025",
        "ccv": "673",
        "ccv_amex": "5040",
        "user_id": "5b57a5d5-2b85-4f27-b9df-dcb00e87f31e",
        "dt_current_timestamp": "2024-01-17 20:09:47"
    },
    {
        "id": 8799,
        "uid": "19eccd9d-4ab3-4d00-bc2b-97be48f55ede",
        "valid_card": "9902-1409-6471-5976",
        "token": "tok_visa",
        "invalid_card": "4000000000000044",
        "month": "07",
        "year": "2026",
        "ccv": "928",
        "ccv_amex": "2128",
        "user_id": "56fb402c-7eb1-493e-8adf-ef53d8f5922c",
        "dt_current_timestamp": "2024-01-17 20:09:47"
    },
    {
        "id": 7026,
        "uid": "6c730163-a468-47fe-8208-52b7f85abcdd",
        "valid_card": "9663-4490-9345-6900",
        "token": "tok_mastercard",
        "invalid_card": "4000000000000044",
        "month": "01",
        "year": "2026",
        "ccv": "201",
        "ccv_amex": "3549",
        "user_id": "44b07384-29f5-4e7e-8ccf-2f8de0fa44ec",
        "dt_current_timestamp": "2024-01-17 20:09:47"
    },
    {
        "id": 1437,
        "uid": "25b4b644-681e-44b1-b4c5-39baa71580f8",
        "valid_card": "2526-1144-6636-1608",
        "token": "tok_visa",
        "invalid_card": "4000000000000044",
        "month": "06",
        "year": "2025",
        "ccv": "104",
        "ccv_amex": "8587",
        "user_id": "10d191d8-4dd3-48a9-b883-dc6aa721111a",
        "dt_current_timestamp": "2024-01-17 20:09:47"
    },
    {
        "id": 5785,
        "uid": "db999abc-0b1f-47c6-a6ec-769beea07dc6",
        "valid_card": "8538-2062-6470-5397",
        "token": "tok_discover",
        "invalid_card": "4000000000000101",
        "month": "02",
        "year": "2021",
        "ccv": "456",
        "ccv_amex": "3655",
        "user_id": "8a77e04a-5377-4a47-935b-0b85daf12c67",
        "dt_current_timestamp": "2024-01-17 20:09:47"
    },
    {
        "id": 6693,
        "uid": "913ab1ff-ad53-4f6d-b53a-b7853b478c2c",
        "valid_card": "8611-1992-6179-4615",
        "token": "tok_discover",
        "invalid_card": "4000000000000101",
        "month": "08",
        "year": "2022",
        "ccv": "970",
        "ccv_amex": "8784",
        "user_id": "d70e75bb-8e31-4bc8-9dbb-25dc102fe90e",
        "dt_current_timestamp": "2024-01-17 20:09:47"
    },
    {
        "id": 2438,
        "uid": "f3184a30-1e43-4056-b1f2-689deb44972f",
        "valid_card": "7636-7118-9532-9639",
        "token": "tok_discover",
        "invalid_card": "4000000000000028",
        "month": "01",
        "year": "2030",
        "ccv": "911",
        "ccv_amex": "3614",
        "user_id": "811ffa50-4177-401a-95e6-732d85474c40",
        "dt_current_timestamp": "2024-01-17 20:09:47"
    },
    {
        "id": 5171,
        "uid": "59aa8ee3-e471-4da2-b438-281151cb0952",
        "valid_card": "1023-1487-3557-5760",
        "token": "tok_visa",
        "invalid_card": "4000000000000044",
        "month": "03",
        "year": "2024",
        "ccv": "633",
        "ccv_amex": "7509",
        "user_id": "bcff5e1e-80d7-4f2e-b7cb-66472bbeff87",
        "dt_current_timestamp": "2024-01-17 20:09:47"
    },
    {
        "id": 1734,
        "uid": "a8089c29-fba6-454c-a33e-608a87670dd9",
        "valid_card": "4204-2690-9947-3121",
        "token": "tok_discover",
        "invalid_card": "4000000000000044",
        "month": "09",
        "year": "2027",
        "ccv": "395",
        "ccv_amex": "5095",
        "user_id": "b656ed1a-26d1-4ac4-8799-5a7cd0baf15e",
        "dt_current_timestamp": "2024-01-17 20:09:47"
    },
    {
        "id": 3252,
        "uid": "63a6144f-0ecf-459e-9467-1c385fc85652",
        "valid_card": "6371-2016-7581-4221",
        "token": "tok_discover",
        "invalid_card": "4000000000000028",
        "month": "11",
        "year": "2029",
        "ccv": "989",
        "ccv_amex": "7609",
        "user_id": "ff76ce34-77ec-450c-b744-54ab6186d020",
        "dt_current_timestamp": "2024-01-17 20:09:47"
    },
    {
        "id": 2553,
        "uid": "cb77eb50-6930-4f87-8cd8-357251aecdcf",
        "valid_card": "7943-2106-8614-1206",
        "token": "tok_discover",
        "invalid_card": "4000000000000101",
        "month": "11",
        "year": "2023",
        "ccv": "534",
        "ccv_amex": "9206",
        "user_id": "f730f66e-2cc8-4d77-b923-a7734edf31e9",
        "dt_current_timestamp": "2024-01-17 20:09:47"
    },
    {
        "id": 1141,
        "uid": "4a38bea6-993a-455c-ae36-366011129c40",
        "valid_card": "4239-1565-2295-6228",
        "token": "tok_visa",
        "invalid_card": "4000000000000101",
        "month": "09",
        "year": "2021",
        "ccv": "941",
        "ccv_amex": "8141",
        "user_id": "5acffa55-3ff9-4acf-8cd5-980938cf16cf",
        "dt_current_timestamp": "2024-01-17 20:09:47"
    },
    {
        "id": 4923,
        "uid": "0d8d50a8-caca-4f08-b9ad-eb01f43a73a3",
        "valid_card": "6636-9613-4401-5068",
        "token": "tok_mastercard",
        "invalid_card": "4000000000000101",
        "month": "02",
        "year": "2028",
        "ccv": "393",
        "ccv_amex": "8519",
        "user_id": "a74e9a7b-81a5-45c6-b95c-0f911c13cf29",
        "dt_current_timestamp": "2024-01-17 20:09:47"
    },
    {
        "id": 1475,
        "uid": "763e254c-c867-4b42-b181-7d3b02ad121a",
        "valid_card": "6478-8111-9470-4030",
        "token": "tok_visa",
        "invalid_card": "4000000000000044",
        "month": "11",
        "year": "2027",
        "ccv": "146",
        "ccv_amex": "7487",
        "user_id": "4014d848-e5e2-474b-bf3d-405d98d7eb49",
        "dt_current_timestamp": "2024-01-17 20:09:47"
    },
    {
        "id": 4170,
        "uid": "216f026c-ed88-4809-9a5d-d52208f99d46",
        "valid_card": "8320-5068-3447-6800",
        "token": "tok_mastercard",
        "invalid_card": "4000000000000101",
        "month": "05",
        "year": "2024",
        "ccv": "456",
        "ccv_amex": "1409",
        "user_id": "3403e293-1a72-46cc-aff3-1e2db1a7daba",
        "dt_current_timestamp": "2024-01-17 20:09:47"
    },
    {
        "id": 8476,
        "uid": "46648e80-4501-4b3c-b170-8f5a04d87b32",
        "valid_card": "5086-5221-2650-1295",
        "token": "tok_mastercard",
        "invalid_card": "4000000000000044",
        "month": "07",
        "year": "2021",
        "ccv": "409",
        "ccv_amex": "4846",
        "user_id": "c909be81-ce4a-4001-b802-2a61960f8626",
        "dt_current_timestamp": "2024-01-17 20:09:47"
    },
    {
        "id": 1447,
        "uid": "f4e5a71c-8f38-4e10-b059-a655dca7d084",
        "valid_card": "3754-2630-6227-5183",
        "token": "tok_discover",
        "invalid_card": "4000000000000101",
        "month": "06",
        "year": "2025",
        "ccv": "293",
        "ccv_amex": "6767",
        "user_id": "35984af9-1d40-4126-8a90-e3a3e3f8e2ed",
        "dt_current_timestamp": "2024-01-17 20:09:47"
    },
    {
        "id": 9530,
        "uid": "f1018af7-a70c-43cc-8986-f267f27874d6",
        "valid_card": "9436-4028-3141-9095",
        "token": "tok_visa",
        "invalid_card": "4000000000000101",
        "month": "10",
        "year": "2030",
        "ccv": "131",
        "ccv_amex": "3075",
        "user_id": "5596f811-f47d-4133-b8e8-8ca04e55fa48",
        "dt_current_timestamp": "2024-01-17 20:09:47"
    },
    {
        "id": 9249,
        "uid": "14e42d7d-4878-4e91-b24b-1714e2361add",
        "valid_card": "8670-1029-7480-3703",
        "token": "tok_mastercard",
        "invalid_card": "4000000000000101",
        "month": "02",
        "year": "2030",
        "ccv": "230",
        "ccv_amex": "1954",
        "user_id": "8631c835-f62c-4d0b-97bd-017bd53b3a93",
        "dt_current_timestamp": "2024-01-17 20:09:47"
    },
    {
        "id": 4569,
        "uid": "337532b2-6a2a-4829-8fec-2ac9be45f0b4",
        "valid_card": "2703-5005-7738-2344",
        "token": "tok_mastercard",
        "invalid_card": "4000000000000044",
        "month": "12",
        "year": "2028",
        "ccv": "677",
        "ccv_amex": "5429",
        "user_id": "b205da0a-7342-4e71-afe0-f4a4987172b6",
        "dt_current_timestamp": "2024-01-17 20:09:47"
    },
    {
        "id": 1943,
        "uid": "05bc91d8-e1d5-4141-b753-cf07be8ec504",
        "valid_card": "9077-3212-6388-4417",
        "token": "tok_discover",
        "invalid_card": "4000000000000028",
        "month": "07",
        "year": "2024",
        "ccv": "479",
        "ccv_amex": "7865",
        "user_id": "5137b65a-d810-43be-8a9f-04a6f33d4dbe",
        "dt_current_timestamp": "2024-01-17 20:09:47"
    },
    {
        "id": 9538,
        "uid": "dae4d2e0-0f9c-44de-8c77-0e88eed4a8c2",
        "valid_card": "4271-5322-1883-2900",
        "token": "tok_visa",
        "invalid_card": "4000000000000028",
        "month": "05",
        "year": "2030",
        "ccv": "147",
        "ccv_amex": "4143",
        "user_id": "784c9648-bb91-473e-8b43-ae55d6ebb37d",
        "dt_current_timestamp": "2024-01-17 20:09:47"
    },
    {
        "id": 3488,
        "uid": "70e59715-99a5-4666-b99d-71820aa3db6c",
        "valid_card": "8505-7765-3467-1669",
        "token": "tok_discover",
        "invalid_card": "4000000000000028",
        "month": "07",
        "year": "2022",
        "ccv": "961",
        "ccv_amex": "3582",
        "user_id": "6dc91c15-d039-49dd-80d7-5ce8f6572483",
        "dt_current_timestamp": "2024-01-17 20:09:47"
    },
    {
        "id": 5183,
        "uid": "14b9d609-d36b-490a-8b59-ce1726dbec1f",
        "valid_card": "7474-1950-9191-5881",
        "token": "tok_mastercard",
        "invalid_card": "4000000000000101",
        "month": "09",
        "year": "2029",
        "ccv": "128",
        "ccv_amex": "2490",
        "user_id": "6d0d831d-ab95-4842-87f5-0a3233cf8e53",
        "dt_current_timestamp": "2024-01-17 20:09:47"
    },
    {
        "id": 9853,
        "uid": "fdf83a24-7d79-453c-9898-2a57294ab144",
        "valid_card": "8134-9532-5066-4635",
        "token": "tok_mastercard",
        "invalid_card": "4000000000000028",
        "month": "10",
        "year": "2028",
        "ccv": "683",
        "ccv_amex": "1869",
        "user_id": "29cadd39-db50-42e1-a185-6ece28aea095",
        "dt_current_timestamp": "2024-01-17 20:09:47"
    },
    {
        "id": 2211,
        "uid": "a63dd8b7-60fa-4d3f-8b47-b838e65114a2",
        "valid_card": "5741-8515-6858-6057",
        "token": "tok_mastercard",
        "invalid_card": "4000000000000028",
        "month": "11",
        "year": "2025",
        "ccv": "799",
        "ccv_amex": "5570",
        "user_id": "cc3a091d-0604-4ef7-a441-8e2395772b5e",
        "dt_current_timestamp": "2024-01-17 20:09:47"
    },
    {
        "id": 4562,
        "uid": "94f09675-2e08-4676-8936-a60036a41628",
        "valid_card": "6100-8200-6417-8601",
        "token": "tok_mastercard",
        "invalid_card": "4000000000000028",
        "month": "04",
        "year": "2025",
        "ccv": "420",
        "ccv_amex": "9838",
        "user_id": "a0470129-c3ec-4a65-adad-ad4bd0cfc47e",
        "dt_current_timestamp": "2024-01-17 20:09:47"
    },
    {
        "id": 2955,
        "uid": "eff6ef98-0fc4-4018-a4af-03d371dcb44c",
        "valid_card": "3562-3533-1564-1029",
        "token": "tok_discover",
        "invalid_card": "4000000000000101",
        "month": "02",
        "year": "2030",
        "ccv": "549",
        "ccv_amex": "8719",
        "user_id": "f601ea07-3dbc-4164-a0b4-2466794ca266",
        "dt_current_timestamp": "2024-01-17 20:09:47"
    },
    {
        "id": 8027,
        "uid": "b787610f-20ad-43d5-9ea7-7946725622f8",
        "valid_card": "5915-1115-7223-3847",
        "token": "tok_visa",
        "invalid_card": "4000000000000044",
        "month": "05",
        "year": "2024",
        "ccv": "848",
        "ccv_amex": "8101",
        "user_id": "da609a3c-c2e6-452a-896b-b72a6fe8fec3",
        "dt_current_timestamp": "2024-01-17 20:09:47"
    },
    {
        "id": 5102,
        "uid": "9af671a2-f962-4b1f-8b74-c9d8dae0c716",
        "valid_card": "9642-1258-6508-4750",
        "token": "tok_mastercard",
        "invalid_card": "4000000000000101",
        "month": "08",
        "year": "2022",
        "ccv": "183",
        "ccv_amex": "1731",
        "user_id": "523b7b7f-818c-405f-87c2-08eda0044d6a",
        "dt_current_timestamp": "2024-01-17 20:09:47"
    },
    {
        "id": 4105,
        "uid": "5997b55c-6f27-404f-b95a-dc04281240d2",
        "valid_card": "5246-9099-8958-4662",
        "token": "tok_mastercard",
        "invalid_card": "4000000000000101",
        "month": "08",
        "year": "2024",
        "ccv": "340",
        "ccv_amex": "6614",
        "user_id": "8179640a-fcba-4285-aac5-bef4f017fb74",
        "dt_current_timestamp": "2024-01-17 20:09:47"
    },
    {
        "id": 4990,
        "uid": "c23e6f4a-97e4-499f-9330-9ea2cbe7d59e",
        "valid_card": "1985-5168-9035-4828",
        "token": "tok_discover",
        "invalid_card": "4000000000000101",
        "month": "10",
        "year": "2023",
        "ccv": "105",
        "ccv_amex": "5348",
        "user_id": "0fb9b9ed-6e4e-4604-9dd8-cc6e91d250f3",
        "dt_current_timestamp": "2024-01-17 20:09:47"
    },
    {
        "id": 4445,
        "uid": "da27a005-ec20-4fca-8739-56bc534c698e",
        "valid_card": "4343-8060-9821-7279",
        "token": "tok_visa",
        "invalid_card": "4000000000000101",
        "month": "11",
        "year": "2024",
        "ccv": "265",
        "ccv_amex": "1854",
        "user_id": "23494915-fa8b-4a9d-8b5f-3de58868df14",
        "dt_current_timestamp": "2024-01-17 20:09:47"
    },
    {
        "id": 7587,
        "uid": "11279804-b100-449c-85d5-c89693723705",
        "valid_card": "6646-6690-6444-3501",
        "token": "tok_discover",
        "invalid_card": "4000000000000101",
        "month": "12",
        "year": "2027",
        "ccv": "972",
        "ccv_amex": "8731",
        "user_id": "e8977444-230a-4cb1-9db8-1099422fd31c",
        "dt_current_timestamp": "2024-01-17 20:09:47"
    },
    {
        "id": 4876,
        "uid": "7067645b-b0f9-4c87-9b9e-fdc063cfb0c2",
        "valid_card": "7770-8631-7842-3409",
        "token": "tok_discover",
        "invalid_card": "4000000000000044",
        "month": "03",
        "year": "2030",
        "ccv": "903",
        "ccv_amex": "5886",
        "user_id": "70df799b-3059-4337-8178-79d234bd2724",
        "dt_current_timestamp": "2024-01-17 20:09:47"
    },
    {
        "id": 6684,
        "uid": "db8059cd-2785-4b7b-b2da-ce62ec329436",
        "valid_card": "6429-7397-2999-6602",
        "token": "tok_visa",
        "invalid_card": "4000000000000028",
        "month": "06",
        "year": "2025",
        "ccv": "320",
        "ccv_amex": "3845",
        "user_id": "4247a5c7-6464-4614-a704-b06e37a21164",
        "dt_current_timestamp": "2024-01-17 20:09:47"
    },
    {
        "id": 5959,
        "uid": "4be375b6-68e8-4cd6-b99b-1a78954360d7",
        "valid_card": "9496-7586-2329-1503",
        "token": "tok_discover",
        "invalid_card": "4000000000000044",
        "month": "03",
        "year": "2025",
        "ccv": "922",
        "ccv_amex": "4954",
        "user_id": "84d10104-9c76-456a-8167-5314584600c9",
        "dt_current_timestamp": "2024-01-17 20:09:47"
    },
    {
        "id": 6434,
        "uid": "9106c7e8-29f8-443c-bb9b-9bbda476f804",
        "valid_card": "4097-1410-2742-8932",
        "token": "tok_mastercard",
        "invalid_card": "4000000000000044",
        "month": "02",
        "year": "2027",
        "ccv": "803",
        "ccv_amex": "9060",
        "user_id": "ebbe8c59-06f8-4747-8c4c-f816f8318926",
        "dt_current_timestamp": "2024-01-17 20:09:47"
    },
    {
        "id": 8105,
        "uid": "7f1edf53-82ba-4080-967a-693dfd22f438",
        "valid_card": "9791-7520-1186-2378",
        "token": "tok_visa",
        "invalid_card": "4000000000000101",
        "month": "10",
        "year": "2030",
        "ccv": "591",
        "ccv_amex": "4624",
        "user_id": "976908d7-87ea-471d-a4c3-7789fde134c9",
        "dt_current_timestamp": "2024-01-17 20:09:47"
    },
    {
        "id": 4698,
        "uid": "960ebe02-5ce7-4683-ba9f-e3c558e22aee",
        "valid_card": "1481-6654-1929-5334",
        "token": "tok_mastercard",
        "invalid_card": "4000000000000044",
        "month": "10",
        "year": "2021",
        "ccv": "238",
        "ccv_amex": "4157",
        "user_id": "9bf17a8d-7c94-4c0d-aa5b-fc9b1da9ba57",
        "dt_current_timestamp": "2024-01-17 20:09:47"
    },
    {
        "id": 3129,
        "uid": "5eb34255-ba56-4f92-ab07-0358170f3752",
        "valid_card": "2029-5959-6013-3842",
        "token": "tok_visa",
        "invalid_card": "4000000000000044",
        "month": "11",
        "year": "2023",
        "ccv": "499",
        "ccv_amex": "4144",
        "user_id": "5f7c21d8-05b8-4945-a411-4ee9c888bedd",
        "dt_current_timestamp": "2024-01-17 20:09:47"
    },
    {
        "id": 9454,
        "uid": "786ffcda-8ee2-4c9a-8811-9aba03a9432a",
        "valid_card": "3998-3068-2947-4845",
        "token": "tok_discover",
        "invalid_card": "4000000000000044",
        "month": "05",
        "year": "2026",
        "ccv": "302",
        "ccv_amex": "8981",
        "user_id": "ef4df3ab-db44-45c8-82eb-a8f5ab997c1c",
        "dt_current_timestamp": "2024-01-17 20:09:47"
    },
    {
        "id": 3363,
        "uid": "e085fe33-9f85-4d6d-b8e2-fe37df160815",
        "valid_card": "7996-2626-7598-3023",
        "token": "tok_discover",
        "invalid_card": "4000000000000101",
        "month": "02",
        "year": "2026",
        "ccv": "749",
        "ccv_amex": "5834",
        "user_id": "f6e2b1ba-94e3-4892-83e3-2c0b581e6270",
        "dt_current_timestamp": "2024-01-17 20:09:47"
    },
    {
        "id": 3886,
        "uid": "652c07fc-7887-475f-ae5e-336494f7c4dc",
        "valid_card": "1093-9909-8961-1813",
        "token": "tok_visa",
        "invalid_card": "4000000000000028",
        "month": "05",
        "year": "2027",
        "ccv": "173",
        "ccv_amex": "7875",
        "user_id": "ba7d3949-0f60-4272-bcd7-d04bcd69a9c4",
        "dt_current_timestamp": "2024-01-17 20:09:47"
    },
    {
        "id": 9523,
        "uid": "7c23036e-8274-4142-ac96-a93b2b8b9180",
        "valid_card": "1333-4558-9342-8410",
        "token": "tok_mastercard",
        "invalid_card": "4000000000000101",
        "month": "04",
        "year": "2026",
        "ccv": "592",
        "ccv_amex": "6925",
        "user_id": "a4729d5c-f6d3-4778-9dd7-33f76c0e7352",
        "dt_current_timestamp": "2024-01-17 20:09:47"
    },
    {
        "id": 3214,
        "uid": "6137b4c7-ff0f-42d2-b462-5f91a2303116",
        "valid_card": "9477-9570-3747-3079",
        "token": "tok_discover",
        "invalid_card": "4000000000000044",
        "month": "12",
        "year": "2028",
        "ccv": "798",
        "ccv_amex": "7807",
        "user_id": "a8174588-bcc6-4ac7-9cf8-d31d5a252075",
        "dt_current_timestamp": "2024-01-17 20:09:47"
    },
    {
        "id": 4969,
        "uid": "69ccca83-c964-451f-83cb-f97f6051f7f0",
        "valid_card": "2445-4393-1912-3033",
        "token": "tok_discover",
        "invalid_card": "4000000000000044",
        "month": "02",
        "year": "2027",
        "ccv": "949",
        "ccv_amex": "1495",
        "user_id": "ac5d3b56-a0c3-4d7a-b395-e811bfd53068",
        "dt_current_timestamp": "2024-01-17 20:09:47"
    },
    {
        "id": 5978,
        "uid": "57bfeab9-ca03-42de-a8d8-4b6243260955",
        "valid_card": "1384-5433-8435-6546",
        "token": "tok_discover",
        "invalid_card": "4000000000000101",
        "month": "03",
        "year": "2023",
        "ccv": "889",
        "ccv_amex": "6950",
        "user_id": "04ee0254-2b11-4a41-b401-d8af29aa6c1a",
        "dt_current_timestamp": "2024-01-17 20:09:47"
    },
    {
        "id": 9723,
        "uid": "bf2b5c66-a037-4a76-b419-c97cbf56a404",
        "valid_card": "5675-6376-3333-6481",
        "token": "tok_visa",
        "invalid_card": "4000000000000028",
        "month": "11",
        "year": "2028",
        "ccv": "470",
        "ccv_amex": "9428",
        "user_id": "d874a571-57e1-4cb7-8536-d97ed23bf280",
        "dt_current_timestamp": "2024-01-17 20:09:47"
    },
    {
        "id": 1518,
        "uid": "d4a4f6e3-b77a-46ff-a198-92f402a5562c",
        "valid_card": "2493-3538-2765-5828",
        "token": "tok_mastercard",
        "invalid_card": "4000000000000044",
        "month": "09",
        "year": "2024",
        "ccv": "180",
        "ccv_amex": "6832",
        "user_id": "3812c8bc-f6a7-4eb5-8910-3b0ec6963fd1",
        "dt_current_timestamp": "2024-01-17 20:09:47"
    },
    {
        "id": 8540,
        "uid": "e3611dff-1a7a-4062-984b-ac36f69e6aa1",
        "valid_card": "8894-6626-2547-4825",
        "token": "tok_discover",
        "invalid_card": "4000000000000044",
        "month": "01",
        "year": "2030",
        "ccv": "844",
        "ccv_amex": "8827",
        "user_id": "d62d9c20-2e33-4b45-91c4-d00fcb830d54",
        "dt_current_timestamp": "2024-01-17 20:09:47"
    },
    {
        "id": 8563,
        "uid": "4fe2df4e-d63c-4572-aba5-933b2d26c1ea",
        "valid_card": "4850-6643-2444-2878",
        "token": "tok_discover",
        "invalid_card": "4000000000000028",
        "month": "07",
        "year": "2021",
        "ccv": "885",
        "ccv_amex": "6554",
        "user_id": "f8c843fd-2a43-43cf-8899-b7e169e18e13",
        "dt_current_timestamp": "2024-01-17 20:09:47"
    },
    {
        "id": 7104,
        "uid": "275f54dd-d97e-45a9-b261-d4e640691a88",
        "valid_card": "7651-1511-1341-7819",
        "token": "tok_visa",
        "invalid_card": "4000000000000028",
        "month": "09",
        "year": "2021",
        "ccv": "584",
        "ccv_amex": "2365",
        "user_id": "c5c87b17-b807-4fcb-aa68-55833b89d00e",
        "dt_current_timestamp": "2024-01-17 20:09:47"
    },
    {
        "id": 6663,
        "uid": "a6ed6401-510f-41ed-a866-fb66c8a4b491",
        "valid_card": "7117-1152-6830-7419",
        "token": "tok_visa",
        "invalid_card": "4000000000000101",
        "month": "10",
        "year": "2023",
        "ccv": "790",
        "ccv_amex": "4435",
        "user_id": "705a7df9-5555-4ece-8acc-18ee39f635a0",
        "dt_current_timestamp": "2024-01-17 20:09:47"
    },
    {
        "id": 5253,
        "uid": "730c5088-88e6-4014-a464-1603b436a9ca",
        "valid_card": "2452-2164-4365-7940",
        "token": "tok_visa",
        "invalid_card": "4000000000000028",
        "month": "01",
        "year": "2023",
        "ccv": "544",
        "ccv_amex": "4723",
        "user_id": "54de5282-bbca-4f74-9ff9-494d7550dfe1",
        "dt_current_timestamp": "2024-01-17 20:09:47"
    },
    {
        "id": 2213,
        "uid": "8450b4ba-13f4-4440-9c20-1f29da704b7f",
        "valid_card": "8223-6566-2777-6927",
        "token": "tok_mastercard",
        "invalid_card": "4000000000000044",
        "month": "08",
        "year": "2029",
        "ccv": "516",
        "ccv_amex": "9934",
        "user_id": "f26a97b7-5391-4969-9012-cbb06c7fba1f",
        "dt_current_timestamp": "2024-01-17 20:09:47"
    },
    {
        "id": 2219,
        "uid": "a9229242-31bc-4241-8c68-f8cd00d3fdda",
        "valid_card": "5495-9291-7657-8144",
        "token": "tok_discover",
        "invalid_card": "4000000000000101",
        "month": "07",
        "year": "2030",
        "ccv": "289",
        "ccv_amex": "1859",
        "user_id": "04681b72-620c-4db6-97b5-b406947e25ec",
        "dt_current_timestamp": "2024-01-17 20:09:47"
    },
    {
        "id": 9605,
        "uid": "3350771d-4930-4583-9f15-e0bc58d7bab4",
        "valid_card": "6346-9892-5922-8443",
        "token": "tok_mastercard",
        "invalid_card": "4000000000000101",
        "month": "08",
        "year": "2023",
        "ccv": "690",
        "ccv_amex": "5034",
        "user_id": "c58865c2-8315-4e6b-b07e-5d5aeaf1250a",
        "dt_current_timestamp": "2024-01-17 20:09:47"
    },
    {
        "id": 5730,
        "uid": "4e958035-6d38-49db-8a8d-5f7eec28258a",
        "valid_card": "3131-2765-2659-8476",
        "token": "tok_visa",
        "invalid_card": "4000000000000101",
        "month": "07",
        "year": "2026",
        "ccv": "869",
        "ccv_amex": "6647",
        "user_id": "d02f7a77-bbb8-4613-ab2d-5bebb2ee9bd6",
        "dt_current_timestamp": "2024-01-17 20:09:47"
    },
    {
        "id": 7931,
        "uid": "55842b64-ec4e-48aa-a35a-8fc85825a05d",
        "valid_card": "1616-6817-4243-9981",
        "token": "tok_visa",
        "invalid_card": "4000000000000028",
        "month": "07",
        "year": "2023",
        "ccv": "578",
        "ccv_amex": "3089",
        "user_id": "8ccd1b0a-4dac-4100-a8cc-305839f4b61f",
        "dt_current_timestamp": "2024-01-17 20:09:47"
    },
    {
        "id": 7313,
        "uid": "48c1b8f2-81ba-4a78-92db-3574d7fba294",
        "valid_card": "3350-6660-2375-1951",
        "token": "tok_discover",
        "invalid_card": "4000000000000044",
        "month": "08",
        "year": "2022",
        "ccv": "954",
        "ccv_amex": "8398",
        "user_id": "39bef89b-abca-474d-a4c7-85ccd7c23458",
        "dt_current_timestamp": "2024-01-17 20:09:47"
    },
    {
        "id": 4906,
        "uid": "7eae24d9-9230-45f0-a6ef-5b1738ce9799",
        "valid_card": "2066-7271-1160-9966",
        "token": "tok_discover",
        "invalid_card": "4000000000000028",
        "month": "04",
        "year": "2027",
        "ccv": "802",
        "ccv_amex": "3391",
        "user_id": "c9f552db-f69e-4031-8096-947824b2a455",
        "dt_current_timestamp": "2024-01-17 20:09:47"
    },
    {
        "id": 1094,
        "uid": "44b6c4a4-1c0f-41e8-82c3-bdceddc1a15e",
        "valid_card": "4568-5938-4434-7801",
        "token": "tok_visa",
        "invalid_card": "4000000000000101",
        "month": "06",
        "year": "2023",
        "ccv": "901",
        "ccv_amex": "7736",
        "user_id": "d6b4a3b4-6e3e-41b2-95c7-c060c2feb2cc",
        "dt_current_timestamp": "2024-01-17 20:09:47"
    },
    {
        "id": 1740,
        "uid": "1d62bd42-0f35-4cb4-b7bd-662fd506f9c9",
        "valid_card": "8738-7871-8769-8303",
        "token": "tok_mastercard",
        "invalid_card": "4000000000000028",
        "month": "05",
        "year": "2023",
        "ccv": "304",
        "ccv_amex": "3898",
        "user_id": "322a127d-0cda-46cc-9d01-520ac79d6ca1",
        "dt_current_timestamp": "2024-01-17 20:09:47"
    },
    {
        "id": 9949,
        "uid": "e753dd67-bef3-439b-9a1a-07ef8b281108",
        "valid_card": "1921-1960-3654-9361",
        "token": "tok_visa",
        "invalid_card": "4000000000000028",
        "month": "09",
        "year": "2024",
        "ccv": "255",
        "ccv_amex": "6200",
        "user_id": "ff3b3a8d-ca4b-4c85-a19f-1a88b0d25ac7",
        "dt_current_timestamp": "2024-01-17 20:09:47"
    },
    {
        "id": 2798,
        "uid": "81b91f99-3acc-48df-93fa-61cdd936dd69",
        "valid_card": "3442-2838-4179-9615",
        "token": "tok_mastercard",
        "invalid_card": "4000000000000028",
        "month": "09",
        "year": "2022",
        "ccv": "404",
        "ccv_amex": "1686",
        "user_id": "58eee8b9-1cfa-45a3-ab22-674645447fed",
        "dt_current_timestamp": "2024-01-17 20:09:47"
    },
    {
        "id": 2200,
        "uid": "9b28c634-73aa-4601-ab0e-f475c1445659",
        "valid_card": "6228-9186-6284-6895",
        "token": "tok_mastercard",
        "invalid_card": "4000000000000044",
        "month": "10",
        "year": "2028",
        "ccv": "723",
        "ccv_amex": "7942",
        "user_id": "9efb180b-6e82-49b7-828c-4e817c14e072",
        "dt_current_timestamp": "2024-01-17 20:09:47"
    },
    {
        "id": 2786,
        "uid": "fcd86aa1-5909-42c5-8057-3946f460fdaf",
        "valid_card": "7477-9609-3952-4074",
        "token": "tok_discover",
        "invalid_card": "4000000000000044",
        "month": "11",
        "year": "2025",
        "ccv": "229",
        "ccv_amex": "6984",
        "user_id": "7a241665-048b-4c58-8c48-4692e007fad5",
        "dt_current_timestamp": "2024-01-17 20:09:47"
    },
    {
        "id": 4429,
        "uid": "3fbf579f-f9c2-4593-bf47-bd9d08bc3713",
        "valid_card": "2523-7719-7646-7462",
        "token": "tok_mastercard",
        "invalid_card": "4000000000000028",
        "month": "01",
        "year": "2030",
        "ccv": "344",
        "ccv_amex": "7395",
        "user_id": "dd40d76d-c0f2-4ce3-a8f8-2af812d98cc5",
        "dt_current_timestamp": "2024-01-17 20:09:47"
    },
    {
        "id": 6249,
        "uid": "20fa66fd-1b93-40fc-a7c9-b226dda89dc3",
        "valid_card": "4992-1160-9771-2288",
        "token": "tok_discover",
        "invalid_card": "4000000000000101",
        "month": "02",
        "year": "2021",
        "ccv": "793",
        "ccv_amex": "8498",
        "user_id": "d89db9b4-c4cc-43b6-84e3-2fee577ba5b5",
        "dt_current_timestamp": "2024-01-17 20:09:47"
    },
    {
        "id": 2067,
        "uid": "ab62bba7-687e-49b6-898a-e6d44a3aace4",
        "valid_card": "6569-3377-1780-5296",
        "token": "tok_discover",
        "invalid_card": "4000000000000101",
        "month": "06",
        "year": "2030",
        "ccv": "296",
        "ccv_amex": "9398",
        "user_id": "4a97eb38-5af2-4f40-b7df-63ea0b950611",
        "dt_current_timestamp": "2024-01-17 20:09:47"
    },
    {
        "id": 4444,
        "uid": "78f220ee-ab02-4360-94f3-6e785bf6205d",
        "valid_card": "1792-5992-4474-9378",
        "token": "tok_visa",
        "invalid_card": "4000000000000044",
        "month": "02",
        "year": "2024",
        "ccv": "504",
        "ccv_amex": "6515",
        "user_id": "6897f0e7-9acf-41b2-9a81-e4b4c89b427e",
        "dt_current_timestamp": "2024-01-17 20:09:47"
    },
    {
        "id": 9790,
        "uid": "ee6be6f4-929f-4c84-ae65-c30f48b82c56",
        "valid_card": "7534-4178-9553-5894",
        "token": "tok_mastercard",
        "invalid_card": "4000000000000101",
        "month": "11",
        "year": "2027",
        "ccv": "953",
        "ccv_amex": "1878",
        "user_id": "d4f42a28-0260-4714-94c9-91cd44835454",
        "dt_current_timestamp": "2024-01-17 20:09:47"
    },
    {
        "id": 6235,
        "uid": "3cc187ad-cc3d-4e8f-8c42-7cc36bc822e7",
        "valid_card": "4623-2948-7325-1250",
        "token": "tok_visa",
        "invalid_card": "4000000000000101",
        "month": "01",
        "year": "2029",
        "ccv": "872",
        "ccv_amex": "7874",
        "user_id": "bece84f9-f04c-41da-b0d4-daaa1a60c109",
        "dt_current_timestamp": "2024-01-17 20:09:47"
    }
]